changelist_data/__init__.py
changelist_data/changelist.py
changelist_data/file_change.py
changelist_data/storage/__init__.py
changelist_data/storage/changelist_data_storage.py
changelist_data/storage/changelists_storage.py
changelist_data/storage/file_validation.py
changelist_data/storage/storage_type.py
changelist_data/storage/workspace_storage.py
changelist_data/validation/__init__.py
changelist_data/validation/arguments.py
changelist_data/validation/collections.py
changelist_data/xml/__init__.py
changelist_data/xml/base_xml_tree.py
changelist_data/xml/xml_reader.py
changelist_data/xml/changelists/__init__.py
changelist_data/xml/changelists/changelists_reader.py
changelist_data/xml/changelists/changelists_tree.py
changelist_data/xml/changelists/changelists_writer.py
changelist_data/xml/workspace/__init__.py
changelist_data/xml/workspace/workspace_reader.py
changelist_data/xml/workspace/workspace_tree.py
changelist_data/xml/workspace/workspace_writer.py
changelist_data-0.3.2.dist-info/licenses/LICENSE
changelist_data-0.3.2.dist-info/METADATA
changelist_data-0.3.2.dist-info/WHEEL
changelist_data-0.3.2.dist-info/top_level.txt
changelist_data-0.3.2.dist-info/RECORD
